pytris/__init__.py
pytris/api.py
pytris/base_models.py
pytris/endpoints.py
pytris/errors.py
pytris/models.py
pytris/parameters.py
pytris/requests.py
pytris/utilities.py
pytris/version.py
pyTRIS-0.2.6.dist-info/LICENSE
pyTRIS-0.2.6.dist-info/METADATA
pyTRIS-0.2.6.dist-info/WHEEL
pyTRIS-0.2.6.dist-info/top_level.txt
pyTRIS-0.2.6.dist-info/RECORD
