Metadata-Version: 2.1
Name: pyTRIS
Version: 0.2.6
Summary: Simple no-dependencies API wrapper for Highways England's WebTRIS Traffic Flow API
Home-page: https://github.com/asongtoruin/pyTRIS
Author: Adam Ruszkowski
License: UNKNOWN
Project-URL: Documentation, https://asongtoruin.github.io/pyTRIS/
Project-URL: Source, https://github.com/asongtoruin/pyTRIS/
Keywords: transport
Platform: UNKNOWN
Classifier: Development Status :: 3 - Alpha
Classifier: Intended Audience :: Developers
Classifier: License :: OSI Approved :: MIT License
Classifier: Programming Language :: Python :: 3
Classifier: Programming Language :: Python :: 3.6
Classifier: Programming Language :: Python :: 3.7
Classifier: Programming Language :: Python :: 3.8
Classifier: Programming Language :: Python :: 3 :: Only
Requires-Python: >=3.6, <4
